dozer/__init__.py
dozer/leak.py
dozer/logview.py
dozer/profile.py
dozer/reftree.py
dozer/util.py
dozer/media/graphs.html
dozer/media/trace.html
dozer/media/tree.html
dozer/media/css/canviz.css
dozer/media/css/main.css
dozer/media/css/profile.css
dozer/media/images/arrows.gif
dozer/media/images/fade.png
dozer/media/images/pip.gif
dozer/media/javascript/canviz.js
dozer/media/javascript/excanvas.js
dozer/media/javascript/gvcolors.js
dozer/media/javascript/jquery-1.2.6.min.js
dozer/media/javascript/path.js
dozer/media/javascript/prototype.js
dozer/templates/layout.mako
dozer/templates/list_profiles.mako
dozer/templates/logbar.mako
dozer/templates/show_profile.mako
dozer/tests/__init__.py
dozer/tests/test_dozer.py
dozer/tests/test_leak.py
dozer/tests/test_logview.py
dozer/tests/test_profile.py
dozer/tests/test_reftree.py
dozer/tests/test_util.py
dozer-0.9.dist-info/licenses/LICENSE
dozer-0.9.dist-info/METADATA
dozer-0.9.dist-info/WHEEL
dozer-0.9.dist-info/entry_points.txt
dozer-0.9.dist-info/top_level.txt
dozer-0.9.dist-info/RECORD
