Metadata-Version: 2.4
Name: Dozer
Version: 0.9
Summary: WSGI Middleware version of the CherryPy memory leak debugger
Home-page: https://github.com/mgedmin/dozer
Author: Ben Bangert
Author-email: ben@groovie.org
Maintainer: Marius Gedminas
Maintainer-email: marius@gedmin.as
License: CC-PDM-1.0
Keywords: web wsgi memory profiler
Classifier: Development Status :: 3 - Alpha
Classifier: Intended Audience :: Developers
Classifier: Programming Language :: Python :: 3.10
Classifier: Programming Language :: Python :: 3.11
Classifier: Programming Language :: Python :: 3.12
Classifier: Programming Language :: Python :: 3.13
Classifier: Programming Language :: Python :: 3.14
Classifier: Topic :: Internet :: WWW/HTTP
Classifier: Topic :: Internet :: WWW/HTTP :: WSGI
Classifier: Topic :: Software Development :: Libraries :: Python Modules
Requires-Python: >=3.10
License-File: LICENSE
Requires-Dist: WebOb>=1.2
Requires-Dist: Mako
Provides-Extra: test
Requires-Dist: pytest; extra == "test"
Requires-Dist: WebTest; extra == "test"
Requires-Dist: Pillow; extra == "test"
Dynamic: author
Dynamic: author-email
Dynamic: classifier
Dynamic: description
Dynamic: description-content-type
Dynamic: home-page
Dynamic: keywords
Dynamic: license
Dynamic: license-file
Dynamic: maintainer
Dynamic: maintainer-email
Dynamic: provides-extra
Dynamic: requires-dist
Dynamic: requires-python
Dynamic: summary
